md_insights_client/__init__.py
md_insights_client/exceptions.py
md_insights_client/insights_query.py
md_insights_client/insights_snapshot.py
md_insights_client/settings.py
md_insights_client-0.3.1.dist-info/METADATA
md_insights_client-0.3.1.dist-info/WHEEL
md_insights_client-0.3.1.dist-info/entry_points.txt
md_insights_client-0.3.1.dist-info/RECORD
