Metadata-Version: 2.4
Name: md-insights-client
Version: 0.3.1
Summary: OPSWAT MetaDefender InSights API client
Project-URL: Bug Tracker, https://github.com/InQuest/md-insights-client-api/issues
Project-URL: Homepage, https://github.com/InQuest/md-insights-client-api
Author-email: Darren Spruell <darren.spruell@opswat.com>
Classifier: Development Status :: 4 - Beta
Classifier: License :: OSI Approved :: ISC License (ISCL)
Classifier: Programming Language :: Python :: 3
Classifier: Topic :: Security
Requires-Dist: pyyaml==6.0.2
Requires-Dist: requests==2.32.3
Requires-Dist: tabulate==0.9.0
